reacton_redux/__init__.py
reacton_redux/apply_middleware.py
reacton_redux/combine_reducers.py
reacton_redux/compose.py
reacton_redux/create_store.py
reacton_redux/reacton/__init__.py
reacton_redux/reacton/devtools.py
reacton_redux/reacton/reacton.py
reacton_redux/reacton/utils.py
reacton_redux/toolkit/__init__.py
reacton_redux/toolkit/create_action.py
reacton_redux/toolkit/create_reducer.py
reacton_redux/toolkit/immer.py
reacton_redux/types/__init__.py
reacton_redux/types/actions.py
reacton_redux/types/middleware.py
reacton_redux/types/reducers.py
reacton_redux/types/store.py
reacton_redux/utils/__init__.py
reacton_redux/utils/action_types.py
reacton_redux-0.3.0.dist-info/LICENSE
reacton_redux-0.3.0.dist-info/METADATA
reacton_redux-0.3.0.dist-info/WHEEL
reacton_redux-0.3.0.dist-info/RECORD
