Metadata-Version: 2.1
Name: reacton-redux
Version: 0.3.0
Summary: A Python implementation of Redux and Redux Toolkit with bindings for Reacton/Solara
Home-page: https://github.com/egormkn/reacton-redux
License: MIT
Keywords: reacton,redux,solara,voila,jupyter
Author: Egor Makarenko
Author-email: egormkn@yandex.ru
Requires-Python: >=3.8,<4.0
Classifier: Development Status :: 3 - Alpha
Classifier: Framework :: IPython
Classifier: Framework :: Jupyter
Classifier: Intended Audience :: Developers
Classifier: License :: OSI Approved :: MIT License
Classifier: Programming Language :: Python :: 3
Classifier: Programming Language :: Python :: 3.8
Classifier: Programming Language :: Python :: 3.9
Classifier: Programming Language :: Python :: 3.10
Classifier: Programming Language :: Python :: 3.11
Classifier: Programming Language :: Python :: 3.12
Classifier: Topic :: Software Development :: Libraries :: Python Modules
Classifier: Topic :: Software Development :: User Interfaces
Classifier: Topic :: Software Development :: Widget Sets
Provides-Extra: devtools
Requires-Dist: importlib-metadata
Requires-Dist: ipython
Requires-Dist: ipyvuetify ; extra == "devtools"
Requires-Dist: reacton
Requires-Dist: typing-extensions
Project-URL: Repository, https://github.com/egormkn/reacton-redux
